pypdm/__init__.py
pypdm/pdm.py
pypdm-1.1.dist-info/COPYING
pypdm-1.1.dist-info/COPYING.LESSER
pypdm-1.1.dist-info/LICENSE
pypdm-1.1.dist-info/METADATA
pypdm-1.1.dist-info/WHEEL
pypdm-1.1.dist-info/top_level.txt
pypdm-1.1.dist-info/RECORD
