Metadata-Version: 2.1
Name: pypdm
Version: 1.1
Summary: UNKNOWN
Home-page: https://github.com/Ledger-Donjon/pypdm
Author: Olivier Heriveaux
License: UNKNOWN
Platform: UNKNOWN
Requires-Python: >=3.4
Requires-Dist: pyserial
